somfy_mylink/__init__.py
somfy_mylink-0.0.3.dist-info/LICENSE
somfy_mylink-0.0.3.dist-info/METADATA
somfy_mylink-0.0.3.dist-info/WHEEL
somfy_mylink-0.0.3.dist-info/top_level.txt
somfy_mylink-0.0.3.dist-info/RECORD
