Metadata-Version: 2.1
Name: somfy-mylink
Version: 0.0.3
Summary: Python API bindings for the Somfy MyLink Synergy API
Home-page: https://github.com/advait/py-somfy-mylink
Author: Advait Shinde
Author-email: advait.shinde@gmail.com
License: MIT
Platform: UNKNOWN
Classifier: Programming Language :: Python :: 3
Classifier: License :: OSI Approved :: MIT License
Classifier: Operating System :: OS Independent
Classifier: Development Status :: 4 - Beta
Classifier: Topic :: Software Development :: Libraries
